xiaobaiauto/HTMLTestRunner.py
xiaobaiauto/__init__.py
xiaobaiauto/auto.cp38-win_amd64.pyd
xiaobaiauto/autogenertor.cp38-win_amd64.pyd
xiaobaiauto/autorunner.cp38-win_amd64.pyd
xiaobaiauto/genertor.py
xiaobaiauto/runner.py
xiaobaiauto-2.4.1.dist-info/METADATA
xiaobaiauto-2.4.1.dist-info/WHEEL
xiaobaiauto-2.4.1.dist-info/entry_points.txt
xiaobaiauto-2.4.1.dist-info/top_level.txt
xiaobaiauto-2.4.1.dist-info/RECORD
