Metadata-Version: 2.1
Name: xiaobaiauto
Version: 2.4.1
Summary: xiaobaiauto framework 简化Web与接口等自动化实现及日志搜集、报告生成、邮件发送等功能
Home-page: https://gitee.com/big_touch/xiaobaidoc
Author: Tser
Author-email: 807447312@qq.com
License: UNKNOWN
Keywords: xiaobai auto automation test framework
Platform: UNKNOWN
Classifier: Programming Language :: Python :: 3.8
Classifier: License :: OSI Approved :: Apache Software License
Classifier: Operating System :: OS Independent
Requires-Python: >=3.8
Requires-Dist: selenium
Requires-Dist: pyquery
Requires-Dist: requests
Requires-Dist: pyyaml
Requires-Dist: Appium-Python-Client
Requires-Dist: gevent
